Metadata-Version: 2.1
Name: server-report-django_2
Version: 0.1.0
Requires-Dist: django>=5.1.6
Requires-Dist: djangorestframework
